svy_io-0.0.9a0.dist-info/METADATA
svy_io-0.0.9a0.dist-info/WHEEL
svy_io-0.0.9a0.dist-info/licenses/LICENSE.md
svy_io/__init__.py
svy_io/factor.py
svy_io/helpers.py
svy_io/labelled.py
svy_io/metadata.py
svy_io/sas.py
svy_io/spss.py
svy_io/stata.py
svy_io/svyreadstat_rs.abi3.so
svy_io/tagged_na.py
svy_io/temporals.py
svy_io/utils.py
svy_io/zap.py
svy_io-0.0.9a0.dist-info/RECORD
