Metadata-Version: 2.4
Name: svy-io
Version: 0.0.9a0
Classifier: License :: OSI Approved :: MIT License
Requires-Dist: polars>=1.34.0
Requires-Dist: pyarrow>=21
License-File: LICENSE.md
Summary: SAS/SPSS/Stata I/O with Polars, powered by ReadStat + PyO3
Home-Page: https://svylab.com/docs/svy-io
Author: Samplics LLC
Requires-Python: >=3.11
